latex_dependency_scanner/__init__.py
latex_dependency_scanner/_version.py
latex_dependency_scanner/compile.py
latex_dependency_scanner/py.typed
latex_dependency_scanner/scanner.py
latex_dependency_scanner-0.1.3.dist-info/METADATA
latex_dependency_scanner-0.1.3.dist-info/WHEEL
latex_dependency_scanner-0.1.3.dist-info/licenses/LICENSE
latex_dependency_scanner-0.1.3.dist-info/RECORD
