Metadata-Version: 2.3
Name: latex_dependency_scanner
Version: 0.1.3
Summary: Scan LaTeX documents for their dependencies.
Project-URL: Homepage, https://github.com/pytask-dev/latex-dependency-scanner
Project-URL: Changelog, https://github.com/pytask-dev/latex-dependency-scanner/blob/main/CHANGES.md
Project-URL: Documentation, https://github.com/pytask-dev/latex-dependency-scanner
Project-URL: Github, https://github.com/pytask-dev/latex-dependency-scanner
Project-URL: Tracker, https://github.com/pytask-dev/latex-dependency-scanner/issues
Author-email: Tobias Raabe <raabe@posteo.de>
License: MIT
License-File: LICENSE
Classifier: Development Status :: 3 - Alpha
Classifier: License :: OSI Approved :: MIT License
Classifier: Operating System :: OS Independent
Classifier: Programming Language :: Python :: 3
Classifier: Programming Language :: Python :: 3 :: Only
Requires-Python: >=3.8
Provides-Extra: test
Requires-Dist: pytest-cov>=5.0.0; extra == 'test'
Requires-Dist: pytest>=8.1.1; extra == 'test'
Provides-Extra: typing
Requires-Dist: mypy>=1.10.0; extra == 'typing'
